MANIFEST.in
README.md
setup.py
faketime/Makefile
faketime/Makefile.OSX
faketime/__init__.py
faketime/faketime.c
faketime/faketime_common.h
faketime/libfaketime.c
faketime/libfaketime.map
faketime/sunos_endian.h
faketime/time_ops.h
faketime/uthash.h
faketime.egg-info/PKG-INFO
faketime.egg-info/SOURCES.txt
faketime.egg-info/dependency_links.txt
faketime.egg-info/not-zip-safe
faketime.egg-info/top_level.txt