Metadata-Version: 2.1
Name: faketime
Version: 0.9.8
Summary: Libfaketime wrapper.
Home-page: https://github.com/hitchdev/faketime/
Author: Colm O'Connor
Author-email: colm.oconnor.github@gmail.com
License: GPLv2
Keywords: libfaketime faketime
Platform: UNKNOWN
Classifier: Development Status :: 3 - Alpha
Classifier: Intended Audience :: Developers
Classifier: License :: OSI Approved :: GNU Library or Lesser General Public License (LGPL)
Classifier: Topic :: Software Development :: Quality Assurance
Classifier: Topic :: Software Development :: Testing
Classifier: Topic :: Software Development :: Libraries
Classifier: Programming Language :: Python :: 2
Classifier: Programming Language :: Python :: 2.6
Classifier: Programming Language :: Python :: 2.7
Classifier: Programming Language :: Python :: 3
Classifier: Programming Language :: Python :: 3.4
